novamind/__init__.py
novamind/framework/__init__.py
novamind/framework/cifar.py
novamind/framework/framework.py
novamind/framework/mnist.py
novamind/framework/resnet_cifar.py
novamind/framework/vgg.py
novamind/ops/__init__.py
novamind/ops/im_ops.py
novamind/ops/np_ops.py
novamind/ops/text_ops.py
novamind/ops/tf_ops.py
novamind/util/__init__.py
novamind/util/imagenet_classes.py
novamind/util/py_utils.py
novamind-0.0.2.dist-info/LICENSE
novamind-0.0.2.dist-info/METADATA
novamind-0.0.2.dist-info/WHEEL
novamind-0.0.2.dist-info/top_level.txt
novamind-0.0.2.dist-info/RECORD
