Metadata-Version: 2.1
Name: novamind
Version: 0.0.2
Summary: Learning
Home-page: https://github.com/duanyzhi/novamind
Author: Nova Mind
Author-email: duanyzhi@outlook.com
License: UNKNOWN
Platform: UNKNOWN
Classifier: Programming Language :: Python :: 3
Classifier: License :: OSI Approved :: MIT License
Classifier: Operating System :: OS Independent
